midiknobs/__init__.py
midiknobs/__main__.py
midiknobs-0.0.3.dist-info/METADATA
midiknobs-0.0.3.dist-info/WHEEL
midiknobs-0.0.3.dist-info/entry_points.txt
midiknobs-0.0.3.dist-info/top_level.txt
midiknobs-0.0.3.dist-info/RECORD
