Metadata-Version: 2.1
Name: midiknobs
Version: 0.0.3
Summary: A small pyqt5 gui to use midi knobs for change linux master audio
Home-page: UNKNOWN
License: UNKNOWN
Project-URL: Source, https://github.com/nicolalandro/midi_kbobs
Platform: UNKNOWN
Requires-Python: >=3.5
Requires-Dist: python-rtmidi
Requires-Dist: mido
Requires-Dist: vext.pyqt5
Requires-Dist: PyQt5
